README.md
setup.py
glm_saga/__init__.py
glm_saga/elasticnet.py
glm_saga.egg-info/PKG-INFO
glm_saga.egg-info/SOURCES.txt
glm_saga.egg-info/dependency_links.txt
glm_saga.egg-info/requires.txt
glm_saga.egg-info/top_level.txt