Metadata-Version: 2.1
Name: glm-saga
Version: 0.1.2
Summary: A PyTorch solver for elastic net
Home-page: https://github.com/madrylab/glm_saga
Author: Eric Wong
Author-email: wongeric@mit.edu
License: MIT
Platform: any
